fw_utils/__init__.py
fw_utils/datetime.py
fw_utils/dicts.py
fw_utils/files.py
fw_utils/filters.py
fw_utils/formatters.py
fw_utils/json.py
fw_utils/parsers.py
fw_utils/py.typed
fw_utils/state.py
fw_utils/testing.py
fw_utils/middleware/__init__.py
fw_utils/middleware/cache_control.py
fw_utils-5.1.1.dist-info/METADATA
fw_utils-5.1.1.dist-info/WHEEL
fw_utils-5.1.1.dist-info/licenses/LICENSE
fw_utils-5.1.1.dist-info/RECORD
