Metadata-Version: 2.4
Name: fw-utils
Version: 5.1.1
Summary: Common Flywheel helper utilities.
Project-URL: Repository, https://gitlab.com/flywheel-io/tools/lib/fw-utils
Project-URL: Documentation, https://gitlab.com/flywheel-io/tools/lib/fw-utils
Author-email: Flywheel <support@flywheel.io>
License-Expression: MIT
License-File: LICENSE
Keywords: Flywheel,helper,utility
Classifier: Topic :: Software Development :: Libraries :: Python Modules
Requires-Python: <4,>=3.9
Requires-Dist: python-dateutil<3,>=2.8.2
Requires-Dist: tzdata>=2022
Requires-Dist: tzlocal>=4.1
Provides-Extra: all
Requires-Dist: pymongo<5,>=4.8.0; extra == 'all'
Requires-Dist: starlette>=0.41.3; extra == 'all'
